{"users":[{"_id":"63cc2ed0ce117825ed0a9cb3","userId":1133001520,"__v":0},{"_id":"63cc38db90d4469047138678","userId":2094064410,"__v":0},{"_id":"63cc42013aa39589a5996bff","userId":1162514576,"__v":0}],"courses":[{"_id":"63cc2f9b13d0b1936f520c88","url":"https://cloud.mail.ru/public/4XEz/eae3rXuCy/","category":"python","title":"Основы языка python"},{"_id":"63cc2f9b13d0b1936f520c89","title":"Разработка Telegram ботов на python","description":"Udemy Константин Крючков","url":"https://cloud.mail.ru/public/3SZk/eLPJ5TcJ3/","category":"python"},{"_id":"63cc2f9b13d0b1936f520c8a","title":"Мега курс Python","url":"https://cloud.mail.ru/public/554Y/4EUMJUYKY/","category":"python"},{"_id":"63cc2f9b13d0b1936f520c8b","title":"Telegram бот для рассылок JavaScript","url":"https://disk.yandex.ru/d/fGsHcLmE3aLyUx","category":"JavaScript"},{"_id":"63cc2f9b13d0b1936f520c8c","title":"Python для тестировщика","url":"https://cloud.mail.ru/public/Cesr/RDFTzroEv/","category":"python"},{"_id":"63cc2f9b13d0b1936f520c8d","title":"Python для SEO","url":"https://cloud.mail.ru/public/t64J/JSYjmboUH/","category":"python"},{"_id":"63cc2f9b13d0b1936f520c8e","title":"Мастер этического взлома с Python","url":"https://cloud.mail.ru/public/HbFj/2BjzRF93a/","category":"python"},{"_id":"63cc2f9b13d0b1936f520c8f","title":"Изучаем python и взлом систем с нуля","url":"https://cloud.mail.ru/public/4tVK/4Tbw2b48Y/","category":"python"},{"_id":"63cc2f9b13d0b1936f520c90","title":"Познавая верстку HTML, CSS и кое что ещё","url":"https://cloud.mail.ru/public/6xqm/vo8qKfHyL/","category":"Вёрстка HTML CSS","description":"Udemy 2018","comment":"Берёшь этот курс, углубляешь Flex'ы или Grid'ы и можешь работать верстальщиком. Сам с него начинал"},{"_id":"63cc2f9b13d0b1936f520c91","title":"Web разработчик","url":"https://cloud.mail.ru/public/NHvF/549Nhf28h/","category":"Web","comment":"Курс не чекал, но выглядит как все вместе в одном месте, что бы стать разрабом"},{"_id":"63cc2f9b13d0b1936f520c92","title":"Марафон GRID CSS","url":"https://cloud.mail.ru/public/2KkK/3SserNcWC/","category":"Вёрстка HTML CSS","comment":"Надо бы не забыть самому гриды подтянуть"},{"_id":"63cc2f9b13d0b1936f520c93","title":"Интернет-магазин на wordpress + woocommerce","url":"https://cloud.mail.ru/public/4Pmb/Fpgd7Eptd/","category":"wordpress"},{"_id":"63cc300e26bf236d36538cef","title":"Мастер Laravel PHP","url":"https://cloud.mail.ru/public/WTLW/59PyFAeWX/","category":"PHP","description":"для новичков и среднего уровня 2019"},{"_id":"63cc300e26bf236d36538cf0","title":"Nginx","url":"https://cloud.mail.ru/public/6Ejb/sa1W8bHe2/","category":"Web-server","description":"Часть первая (вторая утеряна)","comment":"Для быстрого поднятия nginx под ноду (например) мне помог вот этот видос"},{"_id":"63cc300e26bf236d36538cf1","title":"Nginx, Apache, SSL Encryption - Сертификационный курс для системных администраторов","url":"https://cloud.mail.ru/public/38SH/4kAZKmAqa/","category":"Web-server","description":"Udemy YouAccel Traning 2019"},{"_id":"63cc300e26bf236d36538cf2","title":"Анатомия блокчейна","url":"https://disk.yandex.ru/d/Z80uqPh33QPdxP","category":"Blockchain","description":"Пароль к архиву: www.infosklad.org"},{"_id":"63cc300e26bf236d36538cf3","title":"Адаптация WP","url":"https://cloud.mail.ru/public/6Ukd/ZERReahyn/","category":"wordpress"},{"_id":"63cc300e26bf236d36538cf4","title":"Дизайн и проектирование интерфейсов","url":"https://cloud.mail.ru/public/4jWU/2JBggANUb/","category":"Дизайн"},{"_id":"63cc300e26bf236d36538cf5","title":"Тестировщик ПО","url":"https://cloud.mail.ru/public/kpWX/5qG4QXBVe/","description":"2019","category":"Тестирование"},{"_id":"63cc300e26bf236d36538cf6","title":"Безопасность в сети. Методы взлома и защиты","url":"https://mega.nz/file/94l2kbLS#B-PiBnPOyI9xypx8p-SqwM8S-JT5o1GRBlBV5cRFrg4","category":"Безопасность"},{"_id":"63cc300e26bf236d36538cf7","title":"Практический JavaScript","url":"https://cloud.mail.ru/public/27VL/4XCUVaz5L/","category":"JavaScript","comment":"Для ознакомления с языком подойдут видеокурсы, но набить руку поможет лучший учебник http://code.mu/"},{"_id":"63cc300e26bf236d36538cf8","title":"Node JS","url":"https://cloud.mail.ru/public/ksZk/JVMRkQsiM/","category":"JavaScript","comment":"Курс немного нудный, но польза от него есть. Я его так и не добил. Для познания ноды можно попробовать вот этот учебник http://code.mu/ или видосы Владилена Минина","description":"GeekBrains"},{"_id":"63cc300e26bf236d36538cf9","title":"Комплексное обучение JavaScript","url":"https://cloud.mail.ru/public/Gqx2/odwrV675U/","category":"JavaScript","comment":"Для ознакомления с языком подойдут видеокурсы, но набить руку поможет лучший учебник http://code.mu/"},{"_id":"63cc300e26bf236d36538cfa","title":"Базовый курс JavaScript","url":"https://disk.yandex.ru/d/Geb6hkMtAoj-LQ","category":"JavaScript","comment":"Для ознакомления с языком подойдут видеокурсы, но набить руку поможет лучший учебник http://code.mu/","description":"2020 + дз"},{"_id":"63cc300e26bf236d36538cfb","title":"React JS С нуля до профи, лучшие практики","url":"https://cloud.mail.ru/public/2Xeu/2JNsWjRvi/","description":"Udemy 2020","category":"JavaScript","comment":"Хороший курс, что бы ознакомится и частично понять React. В догонку курсу читайте официальную документацию и смотрите примеры разработки приложений на React по видосам Владилена Минина"},{"_id":"63cc300e26bf236d36538cfc","title":"Курс по веб-дизайну. \"Дизайн-огонь 6.0\". Пакет - designer","url":"https://cloud.mail.ru/public/5am2/4tUZdLgPX/","category":"Дизайн","description":"Алексей Савченко 2019"},{"_id":"63cc300e26bf236d36538cfd","title":"Фреймворк Nuxt JS. Руководство по Full-Stack разработке","url":"https://cloud.mail.ru/public/4KeX/3e2Le7zMQ/","category":"JavaScript","description":"Владилен Минин 2019"},{"_id":"63cc300e26bf236d36538cfe","title":"SQL для всех от нуля до профессионала","url":"https://cloud.mail.ru/public/4fDy/E7c4yrPnZ/","description":"2019","category":"DataBase"},{"_id":"63cc302026bf236d36538cff","title":"Базы данных","url":"https://disk.yandex.com/d/a88r4i2k3VL4eoаcedec3d8","description":"GeekBrains","category":"DataBase"},{"_id":"63cc302026bf236d36538d00","title":"Node JS полное руководство","url":"https://cloud.mail.ru/public/59Qn/52rxPharT/","category":"JavaScript","description":"Там внутри ещё полный курс по веб-разработке"},{"_id":"63cc302026bf236d36538d01","title":"Nest JS с нуля. Современный backend на TypeScript и Node JS","url":"https://cloud.mail.ru/public/6vqV/weRjnQ7mF/","category":"JavaScript","description":"Антон Ларичев Udemy 2021"},{"_id":"63cc302026bf236d36538d02","title":"Курс по моушн дизайну","url":"https://cloud.mail.ru/public/74rH/8moeHnd7q/","category":"Дизайн"},{"_id":"63cc302026bf236d36538d03","title":"Курс грамматики. База английского","url":"https://cloud.mail.ru/public/3Zv4/2CxcyMWtW/","description":"Дмитрий Колесников 2020","category":"Языки","comment":"Прохожу прямо сейчас. Пока что в восторге"},{"_id":"63cc302026bf236d36538d04","title":"TypeScript - полное руководство разработчика","url":"https://cloud.mail.ru/public/Eie1/7cmUeWNeW/","description":"Курс обрезанный и по всем источникам лежит только этот залив.","comment":"Очень крутой спикер, очень круто объясняет, жаль курс не целиком. Ну, в догонку смотреть видосы, читать доку. Если имеете полную версию курса - отпишите автору бота","category":"JavaScript"},{"_id":"63cc302026bf236d36538d05","title":"React+Next JS. TypeScript, Hooks, SSR и CSS GRID","url":"https://cloud.mail.ru/public/yXGU/2PjYzr1WT/","category":"JavaScript","description":"Антон Ларичев 2021"},{"_id":"63cc302026bf236d36538d06","title":"Разработка API на Nest JS","url":"https://cloud.mail.ru/public/ozjN/hL4ZNRHij/","category":"JavaScript","description":"Антон Голошниченко 2021"},{"_id":"63cc302026bf236d36538d07","title":"React Native. Мобильная разработка на JavaScript","url":"https://cloud.mail.ru/public/HzcC/Z32feCLmM/","category":"JavaScript","description":"Владилен Минин 2020"},{"_id":"63cc302026bf236d36538d08","title":"React Native с нуля на практике","url":"https://disk.yandex.ru/d/UOJg5ga4R9iOeg?w=1","category":"JavaScript","description":"Udemy 2021"},{"_id":"63cc302026bf236d36538d09","title":"Современные возможности языка JavaScript","url":"https://cloud.mail.ru/public/LAjz/g56bzgWNb/","category":"JavaScript"},{"_id":"63cc303726bf236d36538d0a","title":"Java от основ до продвинутого","url":"https://cloud.mail.ru/public/CQFu/3SYzytgEC/","category":"Java"},{"_id":"63cc303726bf236d36538d0b","title":"Многопоточность в Java","url":"https://cloud.mail.ru/public/Fhfo/c7Dku3kms/","category":"Java"},{"_id":"63cc303726bf236d36538d0c","title":"Java 2.0","url":"https://disk.yandex.ru/d/YoYSXIwMivZfxХhmh257ep1edd3lys","category":"Java"},{"_id":"63cc303726bf236d36538d0d","title":"Изучение Kotlin","url":"https://cloud.mail.ru/public/29EC/3sBus7Ff3/","category":"Kotlin"},{"_id":"63cc303726bf236d36538d0e","title":"Обучение C# для новичков","url":"https://disk.yandex.ru/d/rh7WrYtqMJsRmgа03a3065d","category":"C#"},{"_id":"63cc303726bf236d36538d0f","title":"C# 6.0","url":"https://cloud.mail.ru/public/J51j/ewoqqtQMe/","category":"C#"},{"_id":"63cc303726bf236d36538d10","title":"Создание игры на Unity и C#","url":"https://cloud.mail.ru/public/4AYw/4jGNfLw3b/","category":"Unity","description":"2D Space Shooter 2019 "},{"_id":"63cc303726bf236d36538d11","title":"Unity для чайников","url":"https://cloud.mail.ru/public/3NgN/3muRTMazq#yxk6098p1edd3ypn","category":"Unity","description":"2019"},{"_id":"63cc303726bf236d36538d12","title":"Шахматы на Unity и C#","url":"https://cloud.mail.ru/public/2poK/52KDUsGid/","category":"Unity"},{"_id":"63cc305126bf236d36538d13","title":"Java + Android","url":"https://cloud.mail.ru/public/57aW/5rfHJ4XTs/","category":"Java"},{"_id":"63cc305126bf236d36538d14","title":"Linux. Администрирование рабочих станций","url":"https://cloud.mail.ru/public/4LqZ/3mowEP7kx/","category":"Linux","description":"2019"},{"_id":"63cc305126bf236d36538d15","title":"Программист Android","url":"https://cloud.mail.ru/public/M2F8/nGRCCoETn/","category":"Java"},{"_id":"63cc305126bf236d36538d16","title":"Тестирование ПО","url":"https://cloud.mail.ru/public/N3QS/MAs88FseW/","category":"Тестирование"},{"_id":"63cc305126bf236d36538d17","title":"Профессия Digital-маркетолог","url":"https://cloud.mail.ru/public/yz6D/F3kbDPXyi/","category":"Маркетинг и продвижение","description":"2019"},{"_id":"63cc305126bf236d36538d18","title":"SMM менеджер (часть 1 из 5)","url":"https://disk.yandex.ru/d/GdGkddO93VbTuc","category":"Маркетинг и продвижение"},{"_id":"63cc305126bf236d36538d19","title":"SMM менеджер (часть 2 из 5)","url":"https://disk.yandex.ru/d/rdjTDiLC3X37Go","category":"Маркетинг и продвижение"},{"_id":"63cc305126bf236d36538d1a","title":"SMM менеджер (часть 3 из 5)","url":"https://disk.yandex.ru/d/JnvuBtWI3Wa7Hw","category":"Маркетинг и продвижение"},{"_id":"63cc305126bf236d36538d1b","title":"SMM менеджер (часть 4 из 5)","url":"https://disk.yandex.ru/d/s8sdy7ZY3WaC9b/THANKS/GROUPS","category":"Маркетинг и продвижение"},{"_id":"63cc305126bf236d36538d1c","title":"SMM менеджер (часть 5 из 5)","url":"https://cloud.mail.ru/public/AUU9/qgc8DxdRV/","category":"Маркетинг и продвижение"},{"_id":"63cc305126bf236d36538d1d","title":"Digital-статегия. Инструменты привлечения и удержания клиентов","url":"https://cloud.mail.ru/public/3sQK/C7P6QDSw8/","category":"Маркетинг и продвижение","description":"2020"},{"_id":"63cc305126bf236d36538d1e","title":"Профессия Веб-Аналитик","url":"https://cloud.mail.ru/public/2j1J/XC2XiTopj/","category":"Маркетинг и продвижение","description":"2020"},{"_id":"63cc306526bf236d36538d1f","title":"Linux & GIT","url":"https://cloud.mail.ru/public/hRFo/Q75iPVXPs","category":"Linux"},{"_id":"63cc306526bf236d36538d20","title":"PHP & SQL","url":"https://cloud.mail.ru/public/ctQH/XjGDMAFh9","category":"PHP"},{"_id":"63cc306526bf236d36538d21","title":"17 курсов по blockchain программированию ","url":"https://cloud.mail.ru/public/4ArH/sZLG47QNt","category":"Blockchain","description":"2017 на английском пароль: www.infosklad.org"},{"_id":"63cc306526bf236d36538d22","title":"Веб-дизайн. От новичка до профи","url":"https://cloud.mail.ru/public/1ox4/omdLrDJHn","category":"Дизайн"},{"_id":"63cc306526bf236d36538d23","title":"Современный веб-дизайн","url":"https://cloud.mail.ru/public/A9Cs/SWitR3nea/","category":"Дизайн","comment":"Там внутри лежит ещё и верстка. Сам не смотрел"},{"_id":"63cc306526bf236d36538d24","title":"Разработка сайта на CMS WordPress (часть 1 из 3)","url":"https://cloud.mail.ru/public/zG6P/jZudy9frp","category":"wordpress","description":"Дмитрий Полос 2020"},{"_id":"63cc306526bf236d36538d25","title":"Разработка сайта на CMS WordPress (часть 2 из 3)","url":"https://cloud.mail.ru/public/C43g/HZechJ5iB","category":"wordpress","description":"Дмитрий Полос 2020"},{"_id":"63cc306526bf236d36538d26","title":"Разработка сайта на CMS WordPress (часть 3 из 3)","url":"https://cloud.mail.ru/public/YyjC/6UeEwfJNA/","category":"wordpress","description":"Дмитрий Полос 2020"},{"_id":"63cc306526bf236d36538d27","title":"Создание веб-серверов","url":"https://cloud.mail.ru/public/83ka/PUqq55NFn","category":"Web-server"},{"_id":"63cc306526bf236d36538d28","title":"GraphQL","url":"https://cloud.mail.ru/public/6bcU/iz5NgzuPZ/","category":"DataBase","description":"2020"},{"_id":"63cc306526bf236d36538d29","title":"GraphQL. Язык запросов для современных веб-приложений","url":"https://cloud.mail.ru/public/2QZT/4EnGVqDRu","category":"DataBase","description":"Книга в pdf"},{"_id":"63cc306526bf236d36538d2a","title":"Ethereum and Solidity. The Complete Developer's Guide","url":"https://drive.google.com/drive/folders/1RJbv3VdOCBmLCoSiU1j3EtBvgaLffIVS","category":"Blockchain"},{"_id":"63cc306526bf236d36538d2b","title":"Node JS практический курс. (MongoDB, GraphQL, MySQL, Express)","url":"https://cloud.mail.ru/public/juEy/fywNyvnjg/","category":"JavaScript"}]}